
{
  "countries": [
    {"country": "Afghanistan", "id": "AFG", "gdp_millions": 14502.16},
    {"country": "Albania", "id": "ALB", "gdp_millions": 22977.68},
    {"country": "Germany", "id": "DEU", "gdp_millions": 4456081.02},
    {"country": "Andorra", "id": "AND", "gdp_millions": 3727.67},
    {"country": "Angola", "id": "AGO", "gdp_millions": 84722.96},
    {"country": "Saudi Arabia", "id": "SAU", "gdp_millions": 1067582.93},
    {"country": "Algeria", "id": "DZA", "gdp_millions": 239899.49},
    {"country": "Argentina", "id": "ARG", "gdp_millions": 640591.41},
    {"country": "Armenia", "id": "ARM", "gdp_millions": 24212.13},
    {"country": "Aruba", "id": "ABW", "gdp_millions": 3544.71},
    {"country": "Australia", "id": "AUS", "gdp_millions": 1723827.22},
    {"country": "Austria", "id": "AUT", "gdp_millions": 516034.14},
    {"country": "Azerbaijan", "id": "AZE", "gdp_millions": 72356.18},
    {"country": "Bahamas", "id": "BHS", "gdp_millions": 14338.50},
    {"country": "Bahrain", "id": "BHR", "gdp_millions": 43205.00},
    {"country": "Bangladesh", "id": "BGD", "gdp_millions": 437415.33},
    {"country": "Barbados", "id": "BRB", "gdp_millions": 6393.56},
    {"country": "Belarus", "id": "BLR", "gdp_millions": 71857.38},
    {"country": "Belgium", "id": "BEL", "gdp_millions": 632216.58},
    {"country": "Belize", "id": "BLZ", "gdp_millions": 3281.50},
    {"country": "Benin", "id": "BEN", "gdp_millions": 19673.28},
    {"country": "Bermuda", "id": "BMU", "gdp_millions": 7827.98},
    {"country": "Bhutan", "id": "BTN", "gdp_millions": 2898.23},
    {"country": "Bolivia", "id": "BOL", "gdp_millions": 45849.83},
    {"country": "Bosnia and Herzegovina", "id": "BIH", "gdp_millions": 27054.89},
    {"country": "Botswana", "id": "BWA", "gdp_millions": 19395.77},
    {"country": "Brazil", "id": "BRA", "gdp_millions": 2173665.66},
    {"country": "Brunei Darussalam", "id": "BRN", "gdp_millions": 15128.29},
    {"country": "Bulgaria", "id": "BGR", "gdp_millions": 101584.38},
    {"country": "Burkina Faso", "id": "BFA", "gdp_millions": 20324.62},
    {"country": "Burundi", "id": "BDI", "gdp_millions": 2642.16},
    {"country": "Cape Verde", "id": "CPV", "gdp_millions": 2587.25},
    {"country": "Cambodia", "id": "KHM", "gdp_millions": 31772.76},
    {"country": "Cameroon", "id": "CMR", "gdp_millions": 47945.51},
    {"country": "Canada", "id": "CAN", "gdp_millions": 2140085.57},
    {"country": "Chad", "id": "TCD", "gdp_millions": 13149.33},
    {"country": "Chile", "id": "CHL", "gdp_millions": 335533.33},
    {"country": "China", "id": "CHN", "gdp_millions": 17794781.99},
    {"country": "Cyprus", "id": "CYP", "gdp_millions": 32229.62},
    {"country": "Colombia", "id": "COL", "gdp_millions": 363540.16},
    {"country": "Comoros", "id": "COM", "gdp_millions": 1352.38},
    {"country": "Democratic Republic of the Congo", "id": "COD", "gdp_millions": 66383.29},
    {"country": "Republic of the Congo", "id": "COG", "gdp_millions": 15321.06},
    {"country": "South Korea", "id": "KOR", "gdp_millions": 1712792.85},
    {"country": "Costa Rica", "id": "CRI", "gdp_millions": 86497.94},
    {"country": "Ivory Coast", "id": "CIV", "gdp_millions": 78788.83},
    {"country": "Croatia", "id": "HRV", "gdp_millions": 82688.84},
    {"country": "Cuba", "id": "CUB", "gdp_millions": 107351.80},
    {"country": "Curacao", "id": "CUW", "gdp_millions": 3073.84},
    {"country": "Denmark", "id": "DNK", "gdp_millions": 404198.76},
    {"country": "Djibouti", "id": "DJI", "gdp_millions": 4098.53},
    {"country": "Dominica", "id": "DMA", "gdp_millions": 653.99},
    {"country": "Ecuador", "id": "ECU", "gdp_millions": 118844.83},
    {"country": "Egypt", "id": "EGY", "gdp_millions": 395926.08},
    {"country": "El Salvador", "id": "SLV", "gdp_millions": 34015.62},
    {"country": "United Arab Emirates", "id": "ARE", "gdp_millions": 504173.45},
    {"country": "Eritrea", "id": "ERI", "gdp_millions": 2065.00},
    {"country": "Slovenia", "id": "SVN", "gdp_millions": 68216.78},
    {"country": "Spain", "id": "ESP", "gdp_millions": 1580694.71},
    {"country": "United States", "id": "USA", "gdp_millions": 27360935.00},
    {"country": "Estonia", "id": "EST", "gdp_millions": 40744.85},
    {"country": "Eswatini", "id": "SWZ", "gdp_millions": 4597.86},
    {"country": "Ethiopia", "id": "ETH", "gdp_millions": 163697.93},
    {"country": "Russia", "id": "RUS", "gdp_millions": 2021421.48},
    {"country": "Fiji", "id": "FJI", "gdp_millions": 5494.80},
    {"country": "Philippines", "id": "PHL", "gdp_millions": 437146.37},
    {"country": "Finland", "id": "FIN", "gdp_millions": 300187.20},
    {"country": "France", "id": "FRA", "gdp_millions": 3030904.09},
    {"country": "Gabon", "id": "GAB", "gdp_millions": 20516.13},
    {"country": "Gambia", "id": "GMB", "gdp_millions": 2346.95},
    {"country": "Georgia", "id": "GEO", "gdp_millions": 27598.00},
    {"country": "Ghana", "id": "GHA", "gdp_millions": 67773.99},
    {"country": "Greece", "id": "GRC", "gdp_millions": 380218.20},
    {"country": "Grenada", "id": "GRD", "gdp_millions": 1122.84},
    {"country": "Guatemala", "id": "GTM", "gdp_millions": 122751.65},
    {"country": "Guinea", "id": "GIN", "gdp_millions": 10558.96},
    {"country": "Guyana", "id": "GUY", "gdp_millions": 3693.46},
    {"country": "Honduras", "id": "HND", "gdp_millions": 40752.00},
    {"country": "Hungary", "id": "HUN", "gdp_millions": 434482.34},
    {"country": "Iceland", "id": "ISL", "gdp_millions": 26863.55},
    {"country": "India", "id": "IND", "gdp_millions": 3282230.28},
    {"country": "Indonesia", "id": "IDN", "gdp_millions": 1479134.73},
    {"country": "Iran", "id": "IRN", "gdp_millions": 1018703.87},
    {"country": "Iraq", "id": "IRQ", "gdp_millions": 365306.84},
    {"country": "Ireland", "id": "IRL", "gdp_millions": 612104.26},
    {"country": "Israel", "id": "ISR", "gdp_millions": 557545.07},
    {"country": "Italy", "id": "ITA", "gdp_millions": 2555922.16},
    {"country": "Jamaica", "id": "JAM", "gdp_millions": 15031.76},
    {"country": "Japan", "id": "JPN", "gdp_millions": 4895324.77},
    {"country": "Jordan", "id": "JOR", "gdp_millions": 129543.95},
    {"country": "Kazakhstan", "id": "KAZ", "gdp_millions": 154413.59},
    {"country": "Kenya", "id": "KEN", "gdp_millions": 136468.04},
    {"country": "Kiribati", "id": "KIR", "gdp_millions": 243.58},
    {"country": "Kuwait", "id": "KWT", "gdp_millions": 91854.87},
    {"country": "Kyrgyzstan", "id": "KGZ", "gdp_millions": 16385.04},
    {"country": "Laos", "id": "LAO", "gdp_millions": 27364.84},
    {"country": "Latvia", "id": "LVA", "gdp_millions": 39723.67},
    {"country": "Lebanon", "id": "LBN", "gdp_millions": 52713.42},
    {"country": "Lesotho", "id": "LSO", "gdp_millions": 2930.18},
    {"country": "Liberia", "id": "LBR", "gdp_millions": 4132.68},
    {"country": "Libya", "id": "LBY", "gdp_millions": 35738.58},
    {"country": "Liechtenstein", "id": "LIE", "gdp_millions": 7287.77},
    {"country": "Lithuania", "id": "LTU", "gdp_millions": 63376.53},
    {"country": "Luxembourg", "id": "LUX", "gdp_millions": 97416.51},
    {"country": "Madagascar", "id": "MDG", "gdp_millions": 14746.46},
    {"country": "Malawi", "id": "MWI", "gdp_millions": 10008.77},
    {"country": "Malaysia", "id": "MYS", "gdp_millions": 486208.38},
    {"country": "Malta", "id": "MLT", "gdp_millions": 18588.71},
    {"country": "Mauritania", "id": "MRT", "gdp_millions": 9297.68},
    {"country": "Mauritius", "id": "MUS", "gdp_millions": 17478.41},
    {"country": "Mexico", "id": "MEX", "gdp_millions": 1318390.04},
    {"country": "Micronesia", "id": "FSM", "gdp_millions": 685.94},
    {"country": "Moldova", "id": "MDA", "gdp_millions": 5354.54},
    {"country": "Monaco", "id": "MCO", "gdp_millions": 8094.43},
    {"country": "Mongolia", "id": "MNG", "gdp_millions": 11971.72},
    {"country": "Montenegro", "id": "MNE", "gdp_millions": 5837.59},
    {"country": "Morocco", "id": "MAR", "gdp_millions": 144302.16},
    {"country": "Mozambique", "id": "MOZ", "gdp_millions": 14450.38},
    {"country": "Myanmar", "id": "MMR", "gdp_millions": 86626.43},
    {"country": "Namibia", "id": "NAM", "gdp_millions": 13068.20},
    {"country": "Nauru", "id": "NRU", "gdp_millions": 131.94},
    {"country": "Nepal", "id": "NPL", "gdp_millions": 42057.90},
    {"country": "Netherlands", "id": "NLD", "gdp_millions": 1031556.53},
    {"country": "New Zealand", "id": "NZL", "gdp_millions": 290516.90},
    {"country": "Nicaragua", "id": "NIC", "gdp_millions": 18753.48},
    {"country": "Niger", "id": "NER", "gdp_millions": 12946.04},
    {"country": "Nigeria", "id": "NGA", "gdp_millions": 538103.91},
    {"country": "North Macedonia", "id": "MKD", "gdp_millions": 17192.00},
    {"country": "Norway", "id": "NOR", "gdp_millions": 527564.71},
    {"country": "Oman", "id": "OMN", "gdp_millions": 82545.00},
    {"country": "Pakistan", "id": "PAK", "gdp_millions": 421146.57},
    {"country": "Palau", "id": "PLW", "gdp_millions": 366.56},
    {"country": "Panama", "id": "PAN", "gdp_millions": 54652.13},
    {"country": "Papua New Guinea", "id": "PNG", "gdp_millions": 23383.55},
    {"country": "Paraguay", "id": "PRY", "gdp_millions": 40907.28},
    {"country": "Peru", "id": "PER", "gdp_millions": 373105.83},
    {"country": "Poland", "id": "POL", "gdp_millions": 743253.66},
    {"country": "Portugal", "id": "PRT", "gdp_millions": 287739.70},
    {"country": "Qatar", "id": "QAT", "gdp_millions": 235321.00},
    {"country": "Romania", "id": "ROU", "gdp_millions": 333973.62},
    {"country": "Russia", "id": "RUS", "gdp_millions": 2021421.48},
    {"country": "Rwanda", "id": "RWA", "gdp_millions": 12468.00},
    {"country": "Saint Kitts and Nevis", "id": "KNA", "gdp_millions": 1246.15},
    {"country": "Saint Lucia", "id": "LCA", "gdp_millions": 1521.78},
    {"country": "Saint Vincent and the Grenadines", "id": "VCT", "gdp_millions": 811.53},
    {"country": "Samoa", "id": "WSM", "gdp_millions": 907.54},
    {"country": "San Marino", "id": "SMR", "gdp_millions": 2383.18},
    {"country": "Sao Tome and Principe", "id": "STP", "gdp_millions": 507.81},
    {"country": "Saudi Arabia", "id": "SAU", "gdp_millions": 1227177.76},
    {"country": "Senegal", "id": "SEN", "gdp_millions": 24213.56},
    {"country": "Serbia", "id": "SRB", "gdp_millions": 41920.84},
    {"country": "Seychelles", "id": "SYC", "gdp_millions": 1392.29},
    {"country": "Sierra Leone", "id": "SLE", "gdp_millions": 4692.88},
    {"country": "Singapore", "id": "SGP", "gdp_millions": 515915.57},
    {"country": "Slovakia", "id": "SVK", "gdp_millions": 143915.37},
    {"country": "Slovenia", "id": "SVN", "gdp_millions": 51607.14},
    {"country": "Solomon Islands", "id": "SLB", "gdp_millions": 1466.45},
    {"country": "Somalia", "id": "SOM", "gdp_millions": 5641.85},
    {"country": "South Africa", "id": "ZAF", "gdp_millions": 436773.56},
    {"country": "South Sudan", "id": "SSD", "gdp_millions": 3978.24},
    {"country": "Spain", "id": "ESP", "gdp_millions": 1742852.84},
    {"country": "Sri Lanka", "id": "LKA", "gdp_millions": 109573.15},
    {"country": "Sudan", "id": "SDN", "gdp_millions": 45108.94},
    {"country": "Suriname", "id": "SUR", "gdp_millions": 2385.86},
    {"country": "Sweden", "id": "SWE", "gdp_millions": 631165.76},
    {"country": "Switzerland", "id": "CHE", "gdp_millions": 923326.13},
    {"country": "Syria", "id": "SYR", "gdp_millions": 62691.64},
    {"country": "Taiwan", "id": "TWN", "gdp_millions": 975834.87},
    {"country": "Tajikistan", "id": "TJK", "gdp_millions": 12440.43},
    {"country": "Tanzania", "id": "TZA", "gdp_millions": 72479.13},
    {"country": "Thailand", "id": "THA", "gdp_millions": 714357.21},
    {"country": "Timor-Leste", "id": "TLS", "gdp_millions": 2292.45},
    {"country": "Togo", "id": "TGO", "gdp_millions": 6912.72},
    {"country": "Tonga", "id": "TON", "gdp_millions": 459.80},
    {"country": "Trinidad and Tobago", "id": "TTO", "gdp_millions": 38248.53},
    {"country": "Tunisia", "id": "TUN", "gdp_millions": 62938.56},
    {"country": "Turkey", "id": "TUR", "gdp_millions": 1119491.65},
    {"country": "Turkmenistan", "id": "TKM", "gdp_millions": 70727.00},
    {"country": "Tuvalu", "id": "TUV", "gdp_millions": 48.69},
    {"country": "Uganda", "id": "UGA", "gdp_millions": 50746.40},
    {"country": "Ukraine", "id": "UKR", "gdp_millions": 542552.73},
    {"country": "United Arab Emirates", "id": "ARE", "gdp_millions": 591964.35},
    {"country": "United Kingdom", "id": "GBR", "gdp_millions": 3177262.59},
    {"country": "United States", "id": "USA", "gdp_millions": 26269920.16},
    {"country": "Uruguay", "id": "URY", "gdp_millions": 49808.64},
    {"country": "Uzbekistan", "id": "UZB", "gdp_millions": 105694.35},
    {"country": "Vanuatu", "id": "VUT", "gdp_millions": 1110.46},
    {"country": "Venezuela", "id": "VEN", "gdp_millions": 31309.93},
    {"country": "Vietnam", "id": "VNM", "gdp_millions": 541380.52},
    {"country": "Yemen", "id": "YEM", "gdp_millions": 22981.07},
    {"country": "Zambia", "id": "ZMB", "gdp_millions": 30685.20},
    {"country": "Zimbabwe", "id": "ZWE", "gdp_millions": 20288.63}
    {
      "countries": [
        {"country": "Afghanistan", "id": "AFG", "gdp_millions": 14502.16},
        {"country": "Albania", "id": "ALB", "gdp_millions": 22977.68},
        {"country": "Germany", "id": "DEU", "gdp_millions": 4456081.02},
        {"country": "Andorra", "id": "AND", "gdp_millions": 3727.67},
        {"country": "Angola", "id": "AGO", "gdp_millions": 84722.96},
        {"country": "Saudi Arabia", "id": "SAU", "gdp_millions": 1067582.93},
        {"country": "Algeria", "id": "DZA", "gdp_millions": 239899.49},
        {"country": "Argentina", "id": "ARG", "gdp_millions": 640591.41},
        {"country": "Armenia", "id": "ARM", "gdp_millions": 24212.13},
        {"country": "Aruba", "id": "ABW", "gdp_millions": 3544.71},
        {"country": "Australia", "id": "AUS", "gdp_millions": 1723827.22},
        {"country": "Austria", "id": "AUT", "gdp_millions": 516034.14},
        {"country": "Azerbaijan", "id": "AZE", "gdp_millions": 72356.18},
        {"country": "Bahamas", "id": "BHS", "gdp_millions": 14338.50},
        {"country": "Bahrain", "id": "BHR", "gdp_millions": 43205.00},
        {"country": "Bangladesh", "id": "BGD", "gdp_millions": 437415.33},
        {"country": "Barbados", "id": "BRB", "gdp_millions": 6393.56},
        {"country": "Belarus", "id": "BLR", "gdp_millions": 71857.38},
        {"country": "Belgium", "id": "BEL", "gdp_millions": 632216.58},
        {"country": "Belize", "id": "BLZ", "gdp_millions": 3281.50},
        {"country": "Benin", "id": "BEN", "gdp_millions": 19673.28},
        {"country": "Bermuda", "id": "BMU", "gdp_millions": 7827.98},
        {"country": "Bhutan", "id": "BTN", "gdp_millions": 2898.23},
        {"country": "Bolivia", "id": "BOL", "gdp_millions": 45849.83},
        {"country": "Bosnia and Herzegovina", "id": "BIH", "gdp_millions": 27054.89},
        {"country": "Botswana", "id": "BWA", "gdp_millions": 19395.77},
        {"country": "Brazil", "id": "BRA", "gdp_millions": 2173665.66},
        {"country": "Brunei Darussalam", "id": "BRN", "gdp_millions": 15128.29},
        {"country": "Bulgaria", "id": "BGR", "gdp_millions": 101584.38},
        {"country": "Burkina Faso", "id": "BFA", "gdp_millions": 20324.62},
        {"country": "Burundi", "id": "BDI", "gdp_millions": 2642.16},
        {"country": "Cape Verde", "id": "CPV", "gdp_millions": 2587.25},
        {"country": "Cambodia", "id": "KHM", "gdp_millions": 31772.76},
        {"country": "Cameroon", "id": "CMR", "gdp_millions": 47945.51},
        {"country": "Canada", "id": "CAN", "gdp_millions": 2140085.57},
        {"country": "Chad", "id": "TCD", "gdp_millions": 13149.33},
        {"country": "Chile", "id": "CHL", "gdp_millions": 335533.33},
        {"country": "China", "id": "CHN", "gdp_millions": 17794781.99},
        {"country": "Cyprus", "id": "CYP", "gdp_millions": 32229.62},
        {"country": "Colombia", "id": "COL", "gdp_millions": 363540.16},
        {"country": "Comoros", "id": "COM", "gdp_millions": 1352.38},
        {"country": "Democratic Republic of the Congo", "id": "COD", "gdp_millions": 66383.29},
        {"country": "Republic of the Congo", "id": "COG", "gdp_millions": 15321.06},
        {"country": "South Korea", "id": "KOR", "gdp_millions": 1712792.85},
        {"country": "Costa Rica", "id": "CRI", "gdp_millions": 86497.94},
        {"country": "Ivory Coast", "id": "CIV", "gdp_millions": 78788.83},
        {"country": "Croatia", "id": "HRV", "gdp_millions": 82688.84},
        {"country": "Cuba", "id": "CUB", "gdp_millions": 107351.80},
        {"country": "Curacao", "id": "CUW", "gdp_millions": 3073.84},
        {"country": "Denmark", "id": "DNK", "gdp_millions": 404198.76},
        {"country": "Djibouti", "id": "DJI", "gdp_millions": 4098.53},
        {"country": "Dominica", "id": "DMA", "gdp_millions": 653.99},
        {"country": "Ecuador", "id": "ECU", "gdp_millions": 118844.83},
        {"country": "Egypt", "id": "EGY", "gdp_millions": 395926.08},
        {"country": "El Salvador", "id": "SLV", "gdp_millions": 34015.62},
        {"country": "United Arab Emirates", "id": "ARE", "gdp_millions": 504173.45},
        {"country": "Eritrea", "id": "ERI", "gdp_millions": 2065.00},
        {"country": "Slovenia", "id": "SVN", "gdp_millions": 68216.78},
        {"country": "Spain", "id": "ESP", "gdp_millions": 1580694.71},
        {"country": "United States", "id": "USA", "gdp_millions": 27360935.00},
        {"country": "Estonia", "id": "EST", "gdp_millions": 40744.85},
        {"country": "Eswatini", "id": "SWZ", "gdp_millions": 4597.86},
        {"country": "Ethiopia", "id": "ETH", "gdp_millions": 163697.93},
        {"country": "Russia", "id": "RUS", "gdp_millions": 2021421.48},
        {"country": "Fiji", "id": "FJI", "gdp_millions": 5494.80},
        {"country": "Philippines", "id": "PHL", "gdp_millions": 437146.37},
        {"country": "Finland", "id": "FIN", "gdp_millions": 300187.20},
        {"country": "France", "id": "FRA", "gdp_millions": 3030904.09},
        {"country": "Gabon", "id": "GAB", "gdp_millions": 20516.13},
        {"country": "Gambia", "id": "GMB", "gdp_millions": 2346.95},
        {"country": "Georgia", "id": "GEO", "gdp_millions": 27598.00},
        {"country": "Ghana", "id": "GHA", "gdp_millions": 67773.99},
        {"country": "Greece", "id": "GRC", "gdp_millions": 380218.20},
        {"country": "Grenada", "id": "GRD", "gdp_millions": 1122.84},
        {"country": "Guatemala", "id": "GTM", "gdp_millions": 122751.65},
        {"country": "Guinea", "id": "GIN", "gdp_millions": 10558.96},
        {"country": "Guyana", "id": "GUY", "gdp_millions": 3693.46},
        {"country": "Honduras", "id": "HND", "gdp_millions": 40752.00},
        {"country": "Hungary", "id": "HUN", "gdp_millions": 434482.34},
        {"country": "Iceland", "id": "ISL", "gdp_millions": 26863.55},
        {"country": "India", "id": "IND", "gdp_millions": 3282230.28},
        {"country": "Indonesia", "id": "IDN", "gdp_millions": 1479134.73},
        {"country": "Iran", "id": "IRN", "gdp_millions": 1018703.87},
        {"country": "Iraq", "id": "IRQ", "gdp_millions": 365306.84},
        {"country": "Ireland", "id": "IRL", "gdp_millions": 612104.26},
        {"country": "Israel", "id": "ISR", "gdp_millions": 557545.07},
        {"country": "Italy", "id": "ITA", "gdp_millions": 2555922.16},
        {"country": "Jamaica", "id": "JAM", "gdp_millions": 15031.76},
        {"country": "Japan", "id": "JPN", "gdp_millions": 4895324.77},
        {"country": "Jordan", "id": "JOR", "gdp_millions": 129543.95},
        {"country": "Kazakhstan", "id": "KAZ", "gdp_millions": 154413.59},
        {"country": "Kenya", "id": "KEN", "gdp_millions": 136468.04},
        {"country": "Kiribati", "id": "KIR", "gdp_millions": 243.58},
        {"country": "Kuwait", "id": "KWT", "gdp_millions": 91854.87},
        {"country": "Kyrgyzstan", "id": "KGZ", "gdp_millions": 16385.04},
        {"country": "Laos", "id": "LAO", "gdp_millions": 27364.84},
        {"country": "Latvia", "id": "LVA", "gdp_millions": 39723.67},
        {"country": "Lebanon", "id": "LBN", "gdp_millions": 52713.42},
        {"country": "Lesotho", "id": "LSO", "gdp_millions": 2930.18},
        {"country": "Liberia", "id": "LBR", "gdp_millions": 4132.68},
        {"country": "Libya", "id": "LBY", "gdp_millions": 35738.58},
        {"country": "Liechtenstein", "id": "LIE", "gdp_millions": 7287.77},
        {"country": "Lithuania", "id": "LTU", "gdp_millions": 63376.53},
        {"country": "Luxembourg", "id": "LUX", "gdp_millions": 97416.51},
        {"country": "Madagascar", "id": "MDG", "gdp_millions": 14746.46},
        {"country": "Malawi", "id": "MWI", "gdp_millions": 10008.77},
        {"country": "Malaysia", "id": "MYS", "gdp_millions": 486208.38},
        {"country": "Malta", "id": "MLT", "gdp_millions": 18588.71},
        {"country": "Mauritania", "id": "MRT", "gdp_millions": 9297.68},
        {"country": "Mauritius", "id": "MUS", "gdp_millions": 17478.41},
        {"country": "Mexico", "id": "MEX", "gdp_millions": 1318390.04},
        {"country": "Micronesia", "id": "FSM", "gdp_millions": 685.94},
        {"country": "Moldova", "id": "MDA", "gdp_millions": 5354.54},
        {"country": "Monaco", "id": "MCO", "gdp_millions": 8094.43},
        {"country": "Mongolia", "id": "MNG", "gdp_millions": 11971.72},
        {"country": "Montenegro", "id": "MNE", "gdp_millions": 5837.59},
        {"country": "Morocco", "id": "MAR", "gdp_millions": 144302.16},
        {"country": "Mozambique", "id": "MOZ", "gdp_millions": 14450.38},
        {"country": "Myanmar", "id": "MMR", "gdp_millions": 86626.43},
        {"country": "Namibia", "id": "NAM", "gdp_millions": 13068.20},
        {"country": "Nauru", "id": "NRU", "gdp_millions": 131.94},
        {"country": "Nepal", "id": "NPL", "gdp_millions": 42057.90},
        {"country": "Netherlands", "id": "NLD", "gdp_millions": 1031556.53},
        {"country": "New Zealand", "id": "NZL", "gdp_millions": 290516.90},
        {"country": "Nicaragua", "id": "NIC", "gdp_millions": 18753.48},
        {"country": "Niger", "id": "NER", "gdp_millions": 12946.04},
        {"country": "Nigeria", "id": "NGA", "gdp_millions": 538103.91},
        {"country": "North Macedonia", "id": "MKD", "gdp_millions": 17192.00},
        {"country": "Norway", "id": "NOR", "gdp_millions": 527564.71},
        {"country": "Oman", "id": "OMN", "gdp_millions": 82545.00},
        {"country": "Pakistan", "id": "PAK", "gdp_millions": 421146.57},
        {"country": "Palau", "id": "PLW", "gdp_millions": 366.56},
        {"country": "Panama", "id": "PAN", "gdp_millions": 54652.13},
        {"country": "Papua New Guinea", "id": "PNG", "gdp_millions": 23383.55},
        {"country": "Paraguay", "id": "PRY", "gdp_millions": 40907.28},
        {"country": "Peru", "id": "PER", "gdp_millions": 373105.83},
        {"country": "Poland", "id": "POL", "gdp_millions": 743253.66},
        {"country": "Portugal", "id": "PRT", "gdp_millions": 287739.70},
        {"country": "Qatar", "id": "QAT", "gdp_millions": 235321.00},
        {"country": "Romania", "id": "ROU", "gdp_millions": 333973.62},
        {"country": "Russia", "id": "RUS", "gdp_millions": 2021421.48},
        {"country": "Rwanda", "id": "RWA", "gdp_millions": 12468.00},
        {"country": "Saint Kitts and Nevis", "id": "KNA", "gdp_millions": 1246.15},
        {"country": "Saint Lucia", "id": "LCA", "gdp_millions": 1521.78},
        {"country": "Saint Vincent and the Grenadines", "id": "VCT", "gdp_millions": 811.53},
        {"country": "Samoa", "id": "WSM", "gdp_millions": 907.54},
        {"country": "San Marino", "id": "SMR", "gdp_millions": 2383.18},
        {"country": "Sao Tome and Principe", "id": "STP", "gdp_millions": 507.81},
        {"country": "Saudi Arabia", "id": "SAU", "gdp_millions": 1227177.76},
        {"country": "Senegal", "id": "SEN", "gdp_millions": 24213.56},
        {"country": "Serbia", "id": "SRB", "gdp_millions": 41920.84},
        {"country": "Seychelles", "id": "SYC", "gdp_millions": 1392.29},
        {"country": "Sierra Leone", "id": "SLE", "gdp_millions": 4692.88},
        {"country": "Singapore", "id": "SGP", "gdp_millions": 515915.57},
        {"country": "Slovakia", "id": "SVK", "gdp_millions": 143915.37},
        {"country": "Slovenia", "id": "SVN", "gdp_millions": 51607.14},
        {"country": "Solomon Islands", "id": "SLB", "gdp_millions": 1466.45},
        {"country": "Somalia", "id": "SOM", "gdp_millions": 5641.85},
        {"country": "South Africa", "id": "ZAF", "gdp_millions": 436773.56},
        {"country": "South Sudan", "id": "SSD", "gdp_millions": 3978.24},
        {"country": "Spain", "id": "ESP", "gdp_millions": 1742852.84},
        {"country": "Sri Lanka", "id": "LKA", "gdp_millions": 109573.15},
        {"country": "Sudan", "id": "SDN", "gdp_millions": 45108.94},
        {"country": "Suriname", "id": "SUR", "gdp_millions": 2385.86},
        {"country": "Sweden", "id": "SWE", "gdp_millions": 631165.76},
        {"country": "Switzerland", "id": "CHE", "gdp_millions": 923326.13},
        {"country": "Syria", "id": "SYR", "gdp_millions": 62691.64},
        {"country": "Taiwan", "id": "TWN", "gdp_millions": 975834.87},
        {"country": "Tajikistan", "id": "TJK", "gdp_millions": 12440.43},
        {"country": "Tanzania", "id": "TZA", "gdp_millions": 72479.13},
        {"country": "Thailand", "id": "THA", "gdp_millions": 714357.21},
        {"country": "Timor-Leste", "id": "TLS", "gdp_millions": 2292.45},
        {"country": "Togo", "id": "TGO", "gdp_millions": 6912.72},
        {"country": "Tonga", "id": "TON", "gdp_millions": 459.80},
        {"country": "Trinidad and Tobago", "id": "TTO", "gdp_millions": 38248.53},
        {"country": "Tunisia", "id": "TUN", "gdp_millions": 62938.56},
        {"country": "Turkey", "id": "TUR", "gdp_millions": 1119491.65},
        {"country": "Turkmenistan", "id": "TKM", "gdp_millions": 70727.00},
        {"country": "Tuvalu", "id": "TUV", "gdp_millions": 48.69},
        {"country": "Uganda", "id": "UGA", "gdp_millions": 50746.40},
        {"country": "Ukraine", "id": "UKR", "gdp_millions": 542552.73},
        {"country": "United Arab Emirates", "id": "ARE", "gdp_millions": 591964.35},
        {"country": "United Kingdom", "id": "GBR", "gdp_millions": 3177262.59},
        {"country": "United States", "id": "USA", "gdp_millions": 26269920.16},
        {"country": "Uruguay", "id": "URY", "gdp_millions": 49808.64},
        {"country": "Uzbekistan", "id": "UZB", "gdp_millions": 105694.35},
        {"country": "Vanuatu", "id": "VUT", "gdp_millions": 1110.46},
        {"country": "Venezuela", "id": "VEN", "gdp_millions": 31309.93},
        {"country": "Vietnam", "id": "VNM", "gdp_millions": 541380.52},
        {"country": "Yemen", "id": "YEM", "gdp_millions": 22981.07},
        {"country": "Zambia", "id": "ZMB", "gdp_millions": 30685.20},
        {"country": "Zimbabwe", "id": "ZWE", "gdp_millions": 20288.63}
    ]